pay_ccavenue/__init__.py
pay_ccavenue/ccavenue.py
pay_ccavenue/models/__init__.py
pay_ccavenue/models/config.py
pay_ccavenue/models/form.py
pay_ccavenue/models/webhook.py
pay_ccavenue-1.1.0.dist-info/METADATA
pay_ccavenue-1.1.0.dist-info/WHEEL
pay_ccavenue-1.1.0.dist-info/licenses/LICENSE
pay_ccavenue-1.1.0.dist-info/RECORD
