Metadata-Version: 2.4
Name: pay_ccavenue
Version: 1.1.0
Summary: A simple library to setup payment integration with CCAvenue
License: MIT
License-File: LICENSE
Keywords: ccavenue,payment,python
Author: Kuldeep Pisda
Author-email: pisdak79@gmail.com
Requires-Python: >=3.9
Classifier: License :: OSI Approved :: MIT License
Classifier: Programming Language :: Python :: 3
Classifier: Programming Language :: Python :: 3.9
Classifier: Programming Language :: Python :: 3.10
Classifier: Programming Language :: Python :: 3.11
Classifier: Programming Language :: Python :: 3.12
Classifier: Programming Language :: Python :: 3.13
Classifier: Programming Language :: Python :: 3.14
Requires-Dist: pycryptodome (==3.12.0)
Project-URL: Documentation, https://github.com/kdpisda/python-pay-ccavenue
Project-URL: Homepage, https://github.com/kdpisda/python-pay-ccavenue
Project-URL: Repository, https://github.com/kdpisda/python-pay-ccavenue
